CHANGES.txt
README.txt
TODO.txt
setup.py
getpaid/__init__.py
getpaid.SalesforceOrderRecorder.egg-info/PKG-INFO
getpaid.SalesforceOrderRecorder.egg-info/SOURCES.txt
getpaid.SalesforceOrderRecorder.egg-info/dependency_links.txt
getpaid.SalesforceOrderRecorder.egg-info/entry_points.txt
getpaid.SalesforceOrderRecorder.egg-info/namespace_packages.txt
getpaid.SalesforceOrderRecorder.egg-info/not-zip-safe
getpaid.SalesforceOrderRecorder.egg-info/requires.txt
getpaid.SalesforceOrderRecorder.egg-info/top_level.txt
getpaid/SalesforceOrderRecorder/LICENSE.GPL
getpaid/SalesforceOrderRecorder/LICENSE.txt
getpaid/SalesforceOrderRecorder/__init__.py
getpaid/SalesforceOrderRecorder/config.py
getpaid/SalesforceOrderRecorder/configure.zcml
getpaid/SalesforceOrderRecorder/i18n.py
getpaid/SalesforceOrderRecorder/interfaces.py
getpaid/SalesforceOrderRecorder/messagefactory_.py
getpaid/SalesforceOrderRecorder/preferences.py
getpaid/SalesforceOrderRecorder/profiles.zcml
getpaid/SalesforceOrderRecorder/version.txt
getpaid/SalesforceOrderRecorder/Extensions/Install.py
getpaid/SalesforceOrderRecorder/Extensions/__init__.py
getpaid/SalesforceOrderRecorder/browser/__init__.py
getpaid/SalesforceOrderRecorder/browser/configlet.py
getpaid/SalesforceOrderRecorder/browser/configure.zcml
getpaid/SalesforceOrderRecorder/browser/resources/salesforce.gif
getpaid/SalesforceOrderRecorder/content/__init__.py
getpaid/SalesforceOrderRecorder/content/salesforceorderrecorder.py
getpaid/SalesforceOrderRecorder/migrations/__init__.py
getpaid/SalesforceOrderRecorder/profiles/default/actionicons.xml
getpaid/SalesforceOrderRecorder/profiles/default/controlpanel.xml
getpaid/SalesforceOrderRecorder/profiles/default/factorytool.xml
getpaid/SalesforceOrderRecorder/profiles/default/propertiestool.xml
getpaid/SalesforceOrderRecorder/profiles/default/skins.xml
getpaid/SalesforceOrderRecorder/skins/getpaid-salesforce-order-recorder_images/getpaid.png
getpaid/SalesforceOrderRecorder/skins/getpaid-salesforce-order-recorder_images/salesforce.gif