Metadata-Version: 1.0
Name: getpaid.SalesforceOrderRecorder
Version: 0.5
Summary: GetPaid plugin allowing for recording orders in Salesforce.com
Home-page: http://code.google.com/p/getpaid
Author: Rob LaRubbio
Author-email: larubbio@gmail.com
License: GPL
Keywords: Zope CMF Plone Salesforce.com CRM integration
Platform: UNKNOWN
Classifier: Programming Language :: Python
Classifier: Topic :: Software Development :: Libraries :: Python Modules
Classifier: Framework :: Plone
